cd_sql/__init__.py
cd_sql/querries.py
cd_sql/sql.py
cd_sql/version.py
cd_sql-0.0.3.dist-info/LICENSE.md
cd_sql-0.0.3.dist-info/LICENSE.txt
cd_sql-0.0.3.dist-info/METADATA
cd_sql-0.0.3.dist-info/WHEEL
cd_sql-0.0.3.dist-info/top_level.txt
cd_sql-0.0.3.dist-info/RECORD
