Metadata-Version: 2.1
Name: cd-sql
Version: 0.0.3
Summary: This Python package provides a simple and intuitive wrapper for SQLAlchemy.
Author-email: Code Docta <codedocta@gmail.com>
License: MIT
Project-URL: homepage, https://codedocta.com
Project-URL: Bug-Reports, https://github.com/codedocta/cd_sql/issues
Project-URL: Source, https://github.com/codedocta/cd_sql/
Classifier: Development Status :: 4 - Beta
Classifier: License :: OSI Approved :: MIT License
Classifier: Programming Language :: Python :: 3
Classifier: Operating System :: OS Independent
Requires-Python: >=3.6
License-File: LICENSE.md
License-File: LICENSE.txt
Requires-Dist: SQLAlchemy ==2.0.23
